{
  "$schema": "https://developer.microsoft.com/json-schemas/fabric/item/report/definition/visualContainer/2.7.0/schema.json",
  "name": "ec7d0487a95261d0e4b0",
  "position": {
    "x": 0,
    "y": 445.65183450429356,
    "z": 1000,
    "height": 260.79625292740047,
    "width": 1269.0085870413741,
    "tabOrder": 1000
  },
  "visual": {
    "visualType": "tableEx",
    "query": {
      "queryState": {
        "Values": {
          "projections": [
            {
              "field": {
                "HierarchyLevel": {
                  "Expression": {
                    "Hierarchy": {
                      "Expression": {
                        "PropertyVariationSource": {
                          "Expression": {
                            "SourceRef": {
                              "Entity": "Planilha Vendas Vs Delivery"
                            }
                          },
                          "Name": "Variation",
                          "Property": "DATA META"
                        }
                      },
                      "Hierarchy": "Hierarquia de datas"
                    }
                  },
                  "Level": "Ano"
                }
              },
              "queryRef": "Tabela1.DATA META.Variation.Hierarquia de datas.Ano",
              "nativeQueryRef": "DATA META Ano"
            },
            {
              "field": {
                "HierarchyLevel": {
                  "Expression": {
                    "Hierarchy": {
                      "Expression": {
                        "PropertyVariationSource": {
                          "Expression": {
                            "SourceRef": {
                              "Entity": "Planilha Vendas Vs Delivery"
                            }
                          },
                          "Name": "Variation",
                          "Property": "DATA META"
                        }
                      },
                      "Hierarchy": "Hierarquia de datas"
                    }
                  },
                  "Level": "Mês"
                }
              },
              "queryRef": "Tabela1.DATA META.Variation.Hierarquia de datas.Mês",
              "nativeQueryRef": "DATA META Mês"
            },
            {
              "field": {
                "Column": {
                  "Expression": {
                    "SourceRef": {
                      "Entity": "Planilha Vendas Vs Delivery"
                    }
                  },
                  "Property": "Protocolo"
                }
              },
              "queryRef": "Tabela1.Protocolo",
              "nativeQueryRef": "Protocolo"
            },
            {
              "field": {
                "Column": {
                  "Expression": {
                    "SourceRef": {
                      "Entity": "Planilha Vendas Vs Delivery"
                    }
                  },
                  "Property": "GP"
                }
              },
              "queryRef": "Planilha Vendas Vs Delivery.GP",
              "nativeQueryRef": "GP"
            },
            {
              "field": {
                "Column": {
                  "Expression": {
                    "SourceRef": {
                      "Entity": "Planilha Vendas Vs Delivery"
                    }
                  },
                  "Property": "Produto"
                }
              },
              "queryRef": "Tabela1.Produto",
              "nativeQueryRef": "Produto"
            },
            {
              "field": {
                "Aggregation": {
                  "Expression": {
                    "Column": {
                      "Expression": {
                        "SourceRef": {
                          "Entity": "Planilha Vendas Vs Delivery"
                        }
                      },
                      "Property": "Valor Total Realizado"
                    }
                  },
                  "Function": 0
                }
              },
              "queryRef": "Sum(Tabela1.Valor Total Realizado)",
              "nativeQueryRef": "Soma de Valor Total Realizado"
            },
            {
              "field": {
                "Column": {
                  "Expression": {
                    "SourceRef": {
                      "Entity": "Planilha Vendas Vs Delivery"
                    }
                  },
                  "Property": "Status Protocolo"
                }
              },
              "queryRef": "Tabela1.Status Protocolo",
              "nativeQueryRef": "Status Protocolo"
            },
            {
              "field": {
                "Column": {
                  "Expression": {
                    "SourceRef": {
                      "Entity": "Planilha Vendas Vs Delivery"
                    }
                  },
                  "Property": "Nome Razão Social"
                }
              },
              "queryRef": "Tabela1.Nome Razão Social",
              "nativeQueryRef": "Nome Razão Social"
            },
            {
              "field": {
                "Column": {
                  "Expression": {
                    "SourceRef": {
                      "Entity": "Planilha Vendas Vs Delivery"
                    }
                  },
                  "Property": "MOTIVO "
                }
              },
              "queryRef": "Tabela1.MOTIVO ",
              "nativeQueryRef": "MOTIVO "
            }
          ]
        }
      },
      "sortDefinition": {
        "sort": [
          {
            "field": {
              "Aggregation": {
                "Expression": {
                  "Column": {
                    "Expression": {
                      "SourceRef": {
                        "Entity": "Planilha Vendas Vs Delivery"
                      }
                    },
                    "Property": "Valor Total Realizado"
                  }
                },
                "Function": 0
              }
            },
            "direction": "Descending"
          }
        ]
      }
    },
    "objects": {
      "grid": [
        {
          "properties": {
            "gridHorizontal": {
              "expr": {
                "Literal": {
                  "Value": "true"
                }
              }
            },
            "outlineStyle": {
              "expr": {
                "Literal": {
                  "Value": "0D"
                }
              }
            }
          }
        }
      ],
      "values": [
        {
          "properties": {
            "fontColorPrimary": {
              "solid": {
                "color": {
                  "expr": {
                    "ThemeDataColor": {
                      "ColorId": 1,
                      "Percent": 0
                    }
                  }
                }
              }
            },
            "fontColorSecondary": {
              "solid": {
                "color": {
                  "expr": {
                    "ThemeDataColor": {
                      "ColorId": 0,
                      "Percent": 0
                    }
                  }
                }
              }
            },
            "backColorPrimary": {
              "solid": {
                "color": {
                  "expr": {
                    "Literal": {
                      "Value": "'#09F25F'"
                    }
                  }
                }
              }
            },
            "backColorSecondary": {
              "solid": {
                "color": {
                  "expr": {
                    "Literal": {
                      "Value": "'#015F09'"
                    }
                  }
                }
              }
            },
            "bold": {
              "expr": {
                "Literal": {
                  "Value": "true"
                }
              }
            }
          }
        }
      ],
      "columnHeaders": [
        {
          "properties": {
            "bold": {
              "expr": {
                "Literal": {
                  "Value": "true"
                }
              }
            },
            "backColor": {
              "solid": {
                "color": {
                  "expr": {
                    "Literal": {
                      "Value": "'#B1EA94'"
                    }
                  }
                }
              }
            },
            "fontColor": {
              "solid": {
                "color": {
                  "expr": {
                    "ThemeDataColor": {
                      "ColorId": 1,
                      "Percent": 0
                    }
                  }
                }
              }
            },
            "italic": {
              "expr": {
                "Literal": {
                  "Value": "true"
                }
              }
            },
            "underline": {
              "expr": {
                "Literal": {
                  "Value": "true"
                }
              }
            },
            "alignment": {
              "expr": {
                "Literal": {
                  "Value": "'Center'"
                }
              }
            }
          }
        }
      ],
      "total": [
        {
          "properties": {
            "fontColor": {
              "solid": {
                "color": {
                  "expr": {
                    "ThemeDataColor": {
                      "ColorId": 1,
                      "Percent": 0
                    }
                  }
                }
              }
            },
            "backColor": {
              "solid": {
                "color": {
                  "expr": {
                    "Literal": {
                      "Value": "'#B1EA94'"
                    }
                  }
                }
              }
            }
          }
        }
      ],
      "columnWidth": [
        {
          "properties": {
            "value": {
              "expr": {
                "Literal": {
                  "Value": "52.10473369810298D"
                }
              }
            }
          },
          "selector": {
            "metadata": "Tabela1.DATA META.Variation.Hierarquia de datas.Mês"
          }
        },
        {
          "properties": {
            "value": {
              "expr": {
                "Literal": {
                  "Value": "73.71217121454991D"
                }
              }
            }
          },
          "selector": {
            "metadata": "Tabela1.Protocolo"
          }
        },
        {
          "properties": {
            "value": {
              "expr": {
                "Literal": {
                  "Value": "113.60744763382468D"
                }
              }
            }
          },
          "selector": {
            "metadata": "Sum(Tabela1.Valor Total Realizado)"
          }
        },
        {
          "properties": {
            "value": {
              "expr": {
                "Literal": {
                  "Value": "412.64299932940196D"
                }
              }
            }
          },
          "selector": {
            "metadata": "Tabela1.Nome Razão Social"
          }
        },
        {
          "properties": {
            "value": {
              "expr": {
                "Literal": {
                  "Value": "90.67659998857467D"
                }
              }
            }
          },
          "selector": {
            "metadata": "Tabela1.Status Protocolo"
          }
        },
        {
          "properties": {
            "value": {
              "expr": {
                "Literal": {
                  "Value": "199.73911750814756D"
                }
              }
            }
          },
          "selector": {
            "metadata": "Tabela1.Produto"
          }
        }
      ]
    },
    "visualContainerObjects": {
      "stylePreset": [
        {
          "properties": {
            "name": {
              "expr": {
                "Literal": {
                  "Value": "'BoldHeaderFlashyRows'"
                }
              }
            }
          }
        }
      ],
      "visualHeader": [
        {
          "properties": {
            "transparency": {
              "expr": {
                "Literal": {
                  "Value": "100D"
                }
              }
            },
            "foreground": {
              "solid": {
                "color": {
                  "expr": {
                    "ThemeDataColor": {
                      "ColorId": 0,
                      "Percent": 0
                    }
                  }
                }
              }
            }
          }
        }
      ],
      "background": [
        {
          "properties": {
            "transparency": {
              "expr": {
                "Literal": {
                  "Value": "100D"
                }
              }
            }
          }
        }
      ],
      "dropShadow": [
        {
          "properties": {
            "show": {
              "expr": {
                "Literal": {
                  "Value": "true"
                }
              }
            },
            "color": {
              "solid": {
                "color": {
                  "expr": {
                    "Literal": {
                      "Value": "'#05F384'"
                    }
                  }
                }
              }
            }
          }
        }
      ]
    },
    "drillFilterOtherVisuals": true
  },
  "filterConfig": {
    "filters": [
      {
        "name": "9e66119e1e37da10b296",
        "field": {
          "Column": {
            "Expression": {
              "SourceRef": {
                "Entity": "Planilha Vendas Vs Delivery"
              }
            },
            "Property": "STATUS AGRUPADO"
          }
        },
        "type": "Categorical",
        "filter": {
          "Version": 2,
          "From": [
            {
              "Name": "t",
              "Entity": "Planilha Vendas Vs Delivery",
              "Type": 0
            }
          ],
          "Where": [
            {
              "Condition": {
                "Not": {
                  "Expression": {
                    "In": {
                      "Expressions": [
                        {
                          "Column": {
                            "Expression": {
                              "SourceRef": {
                                "Source": "t"
                              }
                            },
                            "Property": "STATUS AGRUPADO"
                          }
                        }
                      ],
                      "Values": [
                        [
                          {
                            "Literal": {
                              "Value": "'CANCELADOS'"
                            }
                          }
                        ],
                        [
                          {
                            "Literal": {
                              "Value": "'VENDAS CANCELADAS'"
                            }
                          }
                        ],
                        [
                          {
                            "Literal": {
                              "Value": "'VENDAS NÃO EFETIVAS'"
                            }
                          }
                        ],
                        [
                          {
                            "Literal": {
                              "Value": "null"
                            }
                          }
                        ],
                        [
                          {
                            "Literal": {
                              "Value": "'META'"
                            }
                          }
                        ]
                      ]
                    }
                  }
                }
              }
            }
          ]
        },
        "howCreated": "User",
        "objects": {
          "general": [
            {
              "properties": {
                "isInvertedSelectionMode": {
                  "expr": {
                    "Literal": {
                      "Value": "true"
                    }
                  }
                }
              }
            }
          ]
        }
      },
      {
        "name": "55e33d0f67938bb06537",
        "field": {
          "Column": {
            "Expression": {
              "SourceRef": {
                "Entity": "Planilha Vendas Vs Delivery"
              }
            },
            "Property": "Status Protocolo"
          }
        },
        "type": "Categorical",
        "filter": {
          "Version": 2,
          "From": [
            {
              "Name": "t",
              "Entity": "Planilha Vendas Vs Delivery",
              "Type": 0
            }
          ],
          "Where": [
            {
              "Condition": {
                "Not": {
                  "Expression": {
                    "In": {
                      "Expressions": [
                        {
                          "Column": {
                            "Expression": {
                              "SourceRef": {
                                "Source": "t"
                              }
                            },
                            "Property": "Status Protocolo"
                          }
                        }
                      ],
                      "Values": [
                        [
                          {
                            "Literal": {
                              "Value": "null"
                            }
                          }
                        ],
                        [
                          {
                            "Literal": {
                              "Value": "'EM PRC'"
                            }
                          }
                        ],
                        [
                          {
                            "Literal": {
                              "Value": "'ENTREGUE'"
                            }
                          }
                        ],
                        [
                          {
                            "Literal": {
                              "Value": "'Realizar PRC'"
                            }
                          }
                        ],
                        [
                          {
                            "Literal": {
                              "Value": "'RENOVAÇÂO'"
                            }
                          }
                        ],
                        [
                          {
                            "Literal": {
                              "Value": "'Retornado Bko'"
                            }
                          }
                        ]
                      ]
                    }
                  }
                }
              }
            }
          ]
        },
        "objects": {
          "general": [
            {
              "properties": {
                "isInvertedSelectionMode": {
                  "expr": {
                    "Literal": {
                      "Value": "true"
                    }
                  }
                }
              }
            }
          ]
        }
      },
      {
        "name": "936112301e0d3964cd87",
        "field": {
          "HierarchyLevel": {
            "Expression": {
              "Hierarchy": {
                "Expression": {
                  "PropertyVariationSource": {
                    "Expression": {
                      "SourceRef": {
                        "Entity": "Planilha Vendas Vs Delivery"
                      }
                    },
                    "Name": "Variation",
                    "Property": "DATA META"
                  }
                },
                "Hierarchy": "Hierarquia de datas"
              }
            },
            "Level": "Ano"
          }
        },
        "type": "Advanced"
      },
      {
        "name": "a098c1c9e2012470114d",
        "field": {
          "HierarchyLevel": {
            "Expression": {
              "Hierarchy": {
                "Expression": {
                  "PropertyVariationSource": {
                    "Expression": {
                      "SourceRef": {
                        "Entity": "Planilha Vendas Vs Delivery"
                      }
                    },
                    "Name": "Variation",
                    "Property": "DATA META"
                  }
                },
                "Hierarchy": "Hierarquia de datas"
              }
            },
            "Level": "Mês"
          }
        },
        "type": "Categorical"
      },
      {
        "name": "fc4ba41b8e2b5c784486",
        "field": {
          "Column": {
            "Expression": {
              "SourceRef": {
                "Entity": "Planilha Vendas Vs Delivery"
              }
            },
            "Property": "Protocolo"
          }
        },
        "type": "Categorical"
      },
      {
        "name": "3f8685b09282b9735aee",
        "field": {
          "Column": {
            "Expression": {
              "SourceRef": {
                "Entity": "Planilha Vendas Vs Delivery"
              }
            },
            "Property": "GP"
          }
        },
        "type": "Categorical"
      },
      {
        "name": "6e924289b5339c40a105",
        "field": {
          "Column": {
            "Expression": {
              "SourceRef": {
                "Entity": "Planilha Vendas Vs Delivery"
              }
            },
            "Property": "Produto"
          }
        },
        "type": "Categorical"
      },
      {
        "name": "a8ae04b558060744aebc",
        "field": {
          "Aggregation": {
            "Expression": {
              "Column": {
                "Expression": {
                  "SourceRef": {
                    "Entity": "Planilha Vendas Vs Delivery"
                  }
                },
                "Property": "Valor Total Realizado"
              }
            },
            "Function": 0
          }
        },
        "type": "Advanced"
      },
      {
        "name": "339acaa695a323c8ce03",
        "field": {
          "Column": {
            "Expression": {
              "SourceRef": {
                "Entity": "Planilha Vendas Vs Delivery"
              }
            },
            "Property": "Nome Razão Social"
          }
        },
        "type": "Categorical"
      },
      {
        "name": "8b4d242943a5401cd159",
        "field": {
          "Column": {
            "Expression": {
              "SourceRef": {
                "Entity": "Planilha Vendas Vs Delivery"
              }
            },
            "Property": "MOTIVO "
          }
        },
        "type": "Categorical"
      }
    ]
  }
}